{
  "pre-processor" : {
    "bars" : [ {
      "id" : 0,
      "area" : 1.0,
      "elasticity" : 2.0E11,
      "length" : 1.0,
      "sigma" : 1.6E8
    }, {
      "id" : 1,
      "area" : 2.0,
      "elasticity" : 2.0E11,
      "length" : 2.0,
      "sigma" : 1.6E8
    }, {
      "id" : 2,
      "area" : 2.0,
      "elasticity" : 2.0E11,
      "length" : 2.0,
      "sigma" : 1.6E8
    }, {
      "id" : 3,
      "area" : 1.0,
      "elasticity" : 2.0E11,
      "length" : 1.0,
      "sigma" : 1.6E8
    } ],
    "forces" : [ {
      "id" : 2,
      "value" : 1.0
    } ],
    "loads" : [ {
      "id" : 0,
      "value" : 1.0
    }, {
      "id" : 3,
      "value" : -1.0
    } ],
    "borders" : {
      "left" : true,
      "right" : true
    }
  },
  "processor" : {
    "nxks" : [ ],
    "nxbs" : [ ],
    "uxas" : [ ],
    "uxbs" : [ ],
    "uxcs" : [ ],
    "sigmabs" : [ ],
    "sigmaks" : [ ]
  }
}